questions/__init__.py
questions/MCBandit01/__init__.py
questions/MCBandit01/mc_bandit01.py
questions/MCBandit02/__init__.py
questions/MCBandit02/mc_bandit02.py
questions/MCDP/__init__.py
questions/MCDP/mcdp0.py
questions/MCPID/__init__.py
questions/MCPID/mcpid.py
questions/MCQuestionBank/__init__.py
questions/MCQuestionBank/bank_discretization.py
questions/MCQuestionBank/control_bank.py
questions/MCQuestionBank/dp_bank.py
questions/MCQuestionBank/pid_bank.py
questions/MCQuestionBank/rl.py
questions/MC_Tabular01/__init__.py
questions/MC_Tabular01/mc_tabular01.py
questions/MC_Tabular02/__init__.py
questions/MC_Tabular02/mc_tabular02.py
questions/MC_Tabular03/__init__.py
questions/MC_Tabular03/mc_tabular03.py
questions/bandit_01/__init__.py
questions/bandit_01/bandit_01.py
questions/bellman01/__init__.py
questions/bellman01/bellman01.py
questions/bellman02/__init__.py
questions/bellman02/bellman02.py
questions/discretization_question01/__init__.py
questions/discretization_question01/discretization_question01.py
questions/discretization_question02/__init__.py
questions/discretization_question02/discretization_question02.py
questions/discretization_question03/__init__.py
questions/discretization_question03/discretization_question03.py
questions/dp_question01/__init__.py
questions/dp_question01/dp_question01.py
questions/dp_question02/__init__.py
questions/dp_question02/dp_question02.py
questions/mc_pid02/__init__.py
questions/mc_pid02/mcpid02.py
questions/mc_pid03/__init__.py
questions/mc_pid03/mcpid03.py
questions/program_bandit01/__init__.py
questions/program_bandit01/program_bandit01.py
questions/program_control01/__init__.py
questions/program_control01/program_control01.py
questions/program_dp01/__init__.py
questions/program_dp01/program_dp01.py
questions/program_dp02/__init__.py
questions/program_dp02/program_dp02.py
questions/program_dp03/__init__.py
questions/program_dp03/program_dp03.py
questions/program_lqr01/__init__.py
questions/program_lqr01/program_lqr01.py
exam_02465_questions-0.0.2.dist-info/METADATA
exam_02465_questions-0.0.2.dist-info/WHEEL
exam_02465_questions-0.0.2.dist-info/top_level.txt
exam_02465_questions-0.0.2.dist-info/RECORD
