Metadata-Version: 2.1
Name: exam_02465_questions
Version: 0.0.2
Summary: Exam generator
Author: Tue Herlau
License: See licensing file
